{
  "locked": false,
  "version": -9998,
  "projectFileDependencyGroups": {
    "": [
      "Newtonsoft.Json >= 6.0.6",
      "System.Diagnostics.TraceSource >= 4.0.0-beta-22905",
      "System.Xml.ReaderWriter >= 4.0.10-beta-22821",
      "System.Xml.XDocument >= 4.0.10-beta-22816",
      "DotNetShim >= 1.0.0-*"
    ],
    "DNX,Version=v4.5.1": [
      "framework/System.Data "
    ],
    "DNXCore,Version=v5.0": [
      "System.Collections >= 4.0.10-beta-22816",
      "System.Data.Common >= 4.0.0-beta-*",
      "System.Globalization >= 4.0.10-beta-*",
      "System.Linq >= 4.0.0-beta-22816",
      "System.Net.Http >= 4.0.0-beta-*",
      "System.Runtime.Extensions >= 4.0.0-beta-*",
      "System.Reflection.TypeExtensions >= 4.0.0-beta-*",
      "System.Text.RegularExpressions >= 4.0.10-beta-*",
      "System.Threading >= 4.0.10-beta-22816",
      "Microsoft.CSharp >= 4.0.0-beta-22816"
    ]
  },
  "libraries": {
    "Microsoft.CSharp/4.0.0-beta-22816": {
      "serviceable": false,
      "sha": "FGnaYvmoVLd0QTnOyHfm+C79a9CGqQAoh76Ix9++a4SdeaAB8PgpB2Vi/Uc5jcp491QvPyPQjtXCuhRfqWvNkw==",
      "frameworks": {
        "DNX,Version=v4.5.1": {
          "dependencies": {
            "System.Dynamic.Runtime": "4.0.10-beta-22816",
            "System.Linq.Expressions": "4.0.10-beta-22816",
            "System.Runtime": "4.0.20-beta-22816"
          },
          "frameworkAssemblies": [],
          "runtimeAssemblies": [],
          "compileAssemblies": []
        },
        "DNXCore,Version=v5.0": {
          "dependencies": {
            "System.Dynamic.Runtime": "4.0.10-beta-22816",
            "System.Linq.Expressions": "4.0.10-beta-22816",
            "System.Runtime": "4.0.20-beta-22816"
          },
          "frameworkAssemblies": [],
          "runtimeAssemblies": [
            "lib/aspnetcore50/Microsoft.CSharp.dll"
          ],
          "compileAssemblies": [
            "lib/contract/Microsoft.CSharp.dll"
          ]
        }
      },
      "files": [
        "License.rtf",
        "Microsoft.CSharp.4.0.0-beta-22816.nupkg",
        "Microsoft.CSharp.4.0.0-beta-22816.nupkg.sha512",
        "Microsoft.CSharp.nuspec",
        "lib/aspnetcore50/Microsoft.CSharp.dll",
        "lib/contract/Microsoft.CSharp.dll",
        "lib/net45/_._",
        "lib/portable-wpa81+wp80+win80+net45+aspnetcore50/Microsoft.CSharp.dll"
      ]
    },
    "Newtonsoft.Json/6.0.6": {
      "serviceable": false,
      "sha": "w26uZNyCG5VeoKiEOJ4+9/o8koSofLKwHl7WLreIcp0U6r57L7WiRXmjp8MTKFw6dYNZ9AE0lw69WYbIhUsU9Q==",
      "frameworks": {
        "DNX,Version=v4.5.1": {
          "dependencies": {},
          "frameworkAssemblies": [],
          "runtimeAssemblies": [
            "lib/net45/Newtonsoft.Json.dll"
          ],
          "compileAssemblies": [
            "lib/net45/Newtonsoft.Json.dll"
          ]
        },
        "DNXCore,Version=v5.0": {
          "dependencies": {},
          "frameworkAssemblies": [],
          "runtimeAssemblies": [
            "lib/portable-net45+wp80+win8+wpa81+aspnetcore50/Newtonsoft.Json.dll"
          ],
          "compileAssemblies": [
            "lib/portable-net45+wp80+win8+wpa81+aspnetcore50/Newtonsoft.Json.dll"
          ]
        }
      },
      "files": [
        "Newtonsoft.Json.6.0.6.nupkg",
        "Newtonsoft.Json.6.0.6.nupkg.sha512",
        "Newtonsoft.Json.nuspec",
        "lib/net20/Newtonsoft.Json.dll",
        "lib/net20/Newtonsoft.Json.xml",
        "lib/net35/Newtonsoft.Json.dll",
        "lib/net35/Newtonsoft.Json.xml",
        "lib/net40/Newtonsoft.Json.dll",
        "lib/net40/Newtonsoft.Json.xml",
        "lib/net45/Newtonsoft.Json.dll",
        "lib/net45/Newtonsoft.Json.xml",
        "lib/netcore45/Newtonsoft.Json.dll",
        "lib/netcore45/Newtonsoft.Json.xml",
        "lib/portable-net40+sl5+wp80+win8+wpa81/Newtonsoft.Json.dll",
        "lib/portable-net40+sl5+wp80+win8+wpa81/Newtonsoft.Json.xml",
        "lib/portable-net45+wp80+win8+wpa81+aspnetcore50/Newtonsoft.Json.dll",
        "lib/portable-net45+wp80+win8+wpa81+aspnetcore50/Newtonsoft.Json.xml",
        "tools/install.ps1"
      ]
    },
    "System.Collections/4.0.10-beta-22816": {
      "serviceable": false,
      "sha": "tkVBx0CH/Xunk18S9LvNzPRqbXdIzsHbcGRtePrZCNZ9EUNuXK0dzzUl5q0KUgsQmeyUCDSw+7mwyG/pDGSpAA==",
      "frameworks": {
        "DNX,Version=v4.5.1": {
          "dependencies": {
            "System.Runtime": "4.0.20-beta-22816"
          },
          "frameworkAssemblies": [
            "mscorlib",
            "System",
            "System.Core"
          ],
          "runtimeAssemblies": [
            "lib/net45/System.Collections.dll"
          ],
          "compileAssemblies": [
            "lib/net45/System.Collections.dll"
          ]
        },
        "DNXCore,Version=v5.0": {
          "dependencies": {
            "System.Runtime": "4.0.20-beta-22816"
          },
          "frameworkAssemblies": [],
          "runtimeAssemblies": [
            "lib/aspnetcore50/System.Collections.dll"
          ],
          "compileAssemblies": [
            "lib/contract/System.Collections.dll"
          ]
        }
      },
      "files": [
        "License.rtf",
        "System.Collections.4.0.10-beta-22816.nupkg",
        "System.Collections.4.0.10-beta-22816.nupkg.sha512",
        "System.Collections.nuspec",
        "lib/aspnetcore50/System.Collections.dll",
        "lib/contract/System.Collections.dll",
        "lib/net45/System.Collections.dll",
        "lib/portable-wpa81+wp80+win80+net45+aspnetcore50/System.Collections.dll"
      ]
    },
    "System.Data.Common/4.0.0-beta-22911": {
      "serviceable": false,
      "sha": "gYzdW+ixJ+1CDhUMC2EcLJn+MPxZkJ+PDmJn6ReLawbHIUq7VWwhpjqtlE4Ax38VXN2Mbmyx8bwdcbrbqHv55A==",
      "frameworks": {
        "DNX,Version=v4.5.1": {
          "dependencies": {
            "System.IO": "4.0.0-beta-22911",
            "System.Runtime": "4.0.0-beta-22911",
            "System.Threading.Tasks": "4.0.0-beta-22911"
          },
          "frameworkAssemblies": [],
          "runtimeAssemblies": [
            "lib/net45/System.Data.Common.dll"
          ],
          "compileAssemblies": [
            "lib/net45/System.Data.Common.dll"
          ]
        },
        "DNXCore,Version=v5.0": {
          "dependencies": {
            "System.IO": "4.0.0-beta-22911",
            "System.Runtime": "4.0.0-beta-22911",
            "System.Threading.Tasks": "4.0.0-beta-22911"
          },
          "frameworkAssemblies": [],
          "runtimeAssemblies": [
            "lib/aspnetcore50/System.Data.Common.dll"
          ],
          "compileAssemblies": [
            "lib/contract/System.Data.Common.dll"
          ]
        }
      },
      "files": [
        "License.rtf",
        "System.Data.Common.4.0.0-beta-22911.nupkg",
        "System.Data.Common.4.0.0-beta-22911.nupkg.sha512",
        "System.Data.Common.nuspec",
        "lib/aspnetcore50/System.Data.Common.dll",
        "lib/contract/System.Data.Common.dll",
        "lib/net45/System.Data.Common.dll",
        "lib/portable-wpa81+wp80+win80+net45+aspnetcore50/System.Data.Common.dll"
      ]
    },
    "System.Diagnostics.TraceSource/4.0.0-beta-22905": {
      "serviceable": false,
      "sha": "56GOy4qjwdGZHdZ1GGIvFB2FwrFmIi4KbcePCxgzqSMPtRq+UlPNfOSj1/GE0+EgwTl4eqGTiCAwp4tC+t1jVA==",
      "frameworks": {
        "DNX,Version=v4.5.1": {
          "dependencies": {
            "System.Runtime": "4.0.0-beta-22905"
          },
          "frameworkAssemblies": [],
          "runtimeAssemblies": [
            "lib/net45/System.Diagnostics.TraceSource.dll"
          ],
          "compileAssemblies": [
            "lib/net45/System.Diagnostics.TraceSource.dll"
          ]
        },
        "DNXCore,Version=v5.0": {
          "dependencies": {
            "System.Runtime": "4.0.0-beta-22905"
          },
          "frameworkAssemblies": [],
          "runtimeAssemblies": [
            "lib/aspnetcore50/System.Diagnostics.TraceSource.dll"
          ],
          "compileAssemblies": [
            "lib/contract/System.Diagnostics.TraceSource.dll"
          ]
        }
      },
      "files": [
        "License.rtf",
        "System.Diagnostics.TraceSource.4.0.0-beta-22905.nupkg",
        "System.Diagnostics.TraceSource.4.0.0-beta-22905.nupkg.sha512",
        "System.Diagnostics.TraceSource.nuspec",
        "lib/aspnetcore50/System.Diagnostics.TraceSource.dll",
        "lib/contract/System.Diagnostics.TraceSource.dll",
        "lib/net45/System.Diagnostics.TraceSource.dll",
        "lib/portable-wpa81+wp80+win80+net45+aspnetcore50/System.Diagnostics.TraceSource.dll"
      ]
    },
    "System.Dynamic.Runtime/4.0.10-beta-22816": {
      "serviceable": false,
      "sha": "xPMym5hsntfLf/Gisnvk3t25TaZRvwDF46PaszRlB63WsDbAIUXgrsE4ob8ZKTL7+uyGW1HGwOBVlJCP/J1/hA==",
      "frameworks": {
        "DNX,Version=v4.5.1": {
          "dependencies": {
            "System.Linq.Expressions": "4.0.10-beta-22816",
            "System.ObjectModel": "4.0.10-beta-22816",
            "System.Reflection": "4.0.10-beta-22816",
            "System.Runtime": "4.0.20-beta-22816"
          },
          "frameworkAssemblies": [
            "mscorlib",
            "System.Core"
          ],
          "runtimeAssemblies": [
            "lib/net45/System.Dynamic.Runtime.dll"
          ],
          "compileAssemblies": [
            "lib/net45/System.Dynamic.Runtime.dll"
          ]
        },
        "DNXCore,Version=v5.0": {
          "dependencies": {
            "System.Linq.Expressions": "4.0.10-beta-22816",
            "System.ObjectModel": "4.0.10-beta-22816",
            "System.Reflection": "4.0.10-beta-22816",
            "System.Runtime": "4.0.20-beta-22816"
          },
          "frameworkAssemblies": [],
          "runtimeAssemblies": [
            "lib/aspnetcore50/System.Dynamic.Runtime.dll"
          ],
          "compileAssemblies": [
            "lib/contract/System.Dynamic.Runtime.dll"
          ]
        }
      },
      "files": [
        "License.rtf",
        "System.Dynamic.Runtime.4.0.10-beta-22816.nupkg",
        "System.Dynamic.Runtime.4.0.10-beta-22816.nupkg.sha512",
        "System.Dynamic.Runtime.nuspec",
        "lib/aspnetcore50/System.Dynamic.Runtime.dll",
        "lib/contract/System.Dynamic.Runtime.dll",
        "lib/net45/System.Dynamic.Runtime.dll",
        "lib/portable-wpa81+wp80+win80+net45+aspnetcore50/System.Dynamic.Runtime.dll"
      ]
    },
    "System.Globalization/4.0.10-beta-22911": {
      "serviceable": false,
      "sha": "hwVWKhmuIsPkwGTiHBKEcnnuxSegKyBqaB0sRknOLgx0rb0n2XqsJ/DZIjrUdSJjnjDIUvru98kbHiTVG1o/dQ==",
      "frameworks": {
        "DNX,Version=v4.5.1": {
          "dependencies": {
            "System.Runtime": "4.0.0-beta-22911"
          },
          "frameworkAssemblies": [],
          "runtimeAssemblies": [
            "lib/net45/System.Globalization.dll"
          ],
          "compileAssemblies": [
            "lib/net45/System.Globalization.dll"
          ]
        },
        "DNXCore,Version=v5.0": {
          "dependencies": {
            "System.Runtime": "4.0.0-beta-22911"
          },
          "frameworkAssemblies": [],
          "runtimeAssemblies": [
            "lib/aspnetcore50/System.Globalization.dll"
          ],
          "compileAssemblies": [
            "lib/contract/System.Globalization.dll"
          ]
        }
      },
      "files": [
        "License.rtf",
        "System.Globalization.4.0.10-beta-22911.nupkg",
        "System.Globalization.4.0.10-beta-22911.nupkg.sha512",
        "System.Globalization.nuspec",
        "lib/aspnetcore50/System.Globalization.dll",
        "lib/contract/System.Globalization.dll",
        "lib/net45/System.Globalization.dll",
        "lib/portable-wpa81+wp80+win80+net45+aspnetcore50/System.Globalization.dll"
      ]
    },
    "System.IO/4.0.10-beta-22816": {
      "serviceable": false,
      "sha": "/wVhoi2uVXw5IZFU+JrPlyVgKrtMPtzQaYQ3DKUxH9nqiX64BChTFGNDcwZK3iNWTIWESxJhj9JR3lbqbG/PIg==",
      "frameworks": {
        "DNX,Version=v4.5.1": {
          "dependencies": {
            "System.Runtime": "4.0.20-beta-22816",
            "System.Text.Encoding": "4.0.10-beta-22816",
            "System.Threading.Tasks": "4.0.10-beta-22816"
          },
          "frameworkAssemblies": [
            "mscorlib",
            "System"
          ],
          "runtimeAssemblies": [
            "lib/net45/System.IO.dll"
          ],
          "compileAssemblies": [
            "lib/net45/System.IO.dll"
          ]
        },
        "DNXCore,Version=v5.0": {
          "dependencies": {
            "System.Runtime": "4.0.20-beta-22816",
            "System.Text.Encoding": "4.0.10-beta-22816",
            "System.Threading.Tasks": "4.0.10-beta-22816"
          },
          "frameworkAssemblies": [],
          "runtimeAssemblies": [
            "lib/aspnetcore50/System.IO.dll"
          ],
          "compileAssemblies": [
            "lib/contract/System.IO.dll"
          ]
        }
      },
      "files": [
        "License.rtf",
        "System.IO.4.0.10-beta-22816.nupkg",
        "System.IO.4.0.10-beta-22816.nupkg.sha512",
        "System.IO.nuspec",
        "lib/aspnetcore50/System.IO.dll",
        "lib/contract/System.IO.dll",
        "lib/net45/System.IO.dll",
        "lib/portable-wpa81+wp80+win80+net45+aspnetcore50/System.IO.dll"
      ]
    },
    "System.Linq/4.0.0-beta-22816": {
      "serviceable": false,
      "sha": "zBGJfF48L17zFzfs/B8KI1yQklPul0af4a1auQTyUxjdy/HzppkIfoRgrq3yqV+YIPWDkUxu9U9bwjOj90xLXw==",
      "frameworks": {
        "DNX,Version=v4.5.1": {
          "dependencies": {
            "System.Collections": "4.0.10-beta-22816",
            "System.Runtime": "4.0.20-beta-22816"
          },
          "frameworkAssemblies": [
            "mscorlib",
            "System.Core"
          ],
          "runtimeAssemblies": [
            "lib/net45/System.Linq.dll"
          ],
          "compileAssemblies": [
            "lib/net45/System.Linq.dll"
          ]
        },
        "DNXCore,Version=v5.0": {
          "dependencies": {
            "System.Collections": "4.0.10-beta-22816",
            "System.Runtime": "4.0.20-beta-22816"
          },
          "frameworkAssemblies": [],
          "runtimeAssemblies": [
            "lib/aspnetcore50/System.Linq.dll"
          ],
          "compileAssemblies": [
            "lib/contract/System.Linq.dll"
          ]
        }
      },
      "files": [
        "License.rtf",
        "System.Linq.4.0.0-beta-22816.nupkg",
        "System.Linq.4.0.0-beta-22816.nupkg.sha512",
        "System.Linq.nuspec",
        "lib/aspnetcore50/System.Linq.dll",
        "lib/contract/System.Linq.dll",
        "lib/net45/System.Linq.dll",
        "lib/portable-wpa81+wp80+win80+net45+aspnetcore50/System.Linq.dll"
      ]
    },
    "System.Linq.Expressions/4.0.10-beta-22816": {
      "serviceable": false,
      "sha": "qTu/alZVoEBZRIrbLzVlFSndQyhIEXY+qoBockbsUu98TDtd1N9gYiyg7FHeW7Qx1vDGfz1PWfUlYBd4G/ZHkg==",
      "frameworks": {
        "DNX,Version=v4.5.1": {
          "dependencies": {
            "System.Reflection": "4.0.10-beta-22816",
            "System.Runtime": "4.0.20-beta-22816"
          },
          "frameworkAssemblies": [
            "mscorlib",
            "System.Core"
          ],
          "runtimeAssemblies": [
            "lib/net45/System.Linq.Expressions.dll"
          ],
          "compileAssemblies": [
            "lib/net45/System.Linq.Expressions.dll"
          ]
        },
        "DNXCore,Version=v5.0": {
          "dependencies": {
            "System.Reflection": "4.0.10-beta-22816",
            "System.Runtime": "4.0.20-beta-22816"
          },
          "frameworkAssemblies": [],
          "runtimeAssemblies": [
            "lib/aspnetcore50/System.Linq.Expressions.dll"
          ],
          "compileAssemblies": [
            "lib/contract/System.Linq.Expressions.dll"
          ]
        }
      },
      "files": [
        "License.rtf",
        "System.Linq.Expressions.4.0.10-beta-22816.nupkg",
        "System.Linq.Expressions.4.0.10-beta-22816.nupkg.sha512",
        "System.Linq.Expressions.nuspec",
        "lib/aspnetcore50/System.Linq.Expressions.dll",
        "lib/contract/System.Linq.Expressions.dll",
        "lib/net45/System.Linq.Expressions.dll",
        "lib/portable-wpa81+wp80+win80+net45+aspnetcore50/System.Linq.Expressions.dll"
      ]
    },
    "System.Net.Http/4.0.0-beta-22911": {
      "serviceable": false,
      "sha": "mMMOTA+YjlK9w1BqWJV/fmmOB2pil/FSxGw7OGu07H20CkWGtne21LjhXtAhBVZnZh2xMwc81pPfxAdxqor/Tg==",
      "frameworks": {
        "DNX,Version=v4.5.1": {
          "dependencies": {
            "System.IO": "4.0.0-beta-22911",
            "System.Net.Primitives": "4.0.0-beta-22911",
            "System.Runtime": "4.0.0-beta-22911",
            "System.Text.Encoding": "4.0.0-beta-22911",
            "System.Threading.Tasks": "4.0.0-beta-22911"
          },
          "frameworkAssemblies": [],
          "runtimeAssemblies": [],
          "compileAssemblies": []
        },
        "DNXCore,Version=v5.0": {
          "dependencies": {
            "System.IO": "4.0.0-beta-22911",
            "System.Net.Primitives": "4.0.0-beta-22911",
            "System.Runtime": "4.0.0-beta-22911",
            "System.Text.Encoding": "4.0.0-beta-22911",
            "System.Threading.Tasks": "4.0.0-beta-22911"
          },
          "frameworkAssemblies": [],
          "runtimeAssemblies": [
            "lib/aspnetcore50/System.Net.Http.dll"
          ],
          "compileAssemblies": [
            "lib/contract/System.Net.Http.dll"
          ]
        }
      },
      "files": [
        "License.rtf",
        "System.Net.Http.4.0.0-beta-22911.nupkg",
        "System.Net.Http.4.0.0-beta-22911.nupkg.sha512",
        "System.Net.Http.nuspec",
        "lib/aspnetcore50/System.Net.Http.dll",
        "lib/contract/System.Net.Http.dll",
        "lib/net45/_._",
        "lib/portable-wpa81+wp80+win80+net45+aspnetcore50/System.Net.Http.dll"
      ]
    },
    "System.Net.Primitives/4.0.10-beta-22231": {
      "serviceable": false,
      "sha": "yEp9GSi3pBe4U441mp8nVWJyxpIMDqwe4neH8T6z/C8t7nmLb/BS+y4rAmemKy+hmazyb3SSZKnjKP3wrAtg0g==",
      "frameworks": {
        "DNX,Version=v4.5.1": {
          "dependencies": {
            "System.Runtime": "4.0.0-beta-22231",
            "System.Runtime.Handles": "4.0.0-beta-22231"
          },
          "frameworkAssemblies": [],
          "runtimeAssemblies": [],
          "compileAssemblies": []
        },
        "DNXCore,Version=v5.0": {
          "dependencies": {
            "System.Runtime": "4.0.0-beta-22231",
            "System.Runtime.Handles": "4.0.0-beta-22231"
          },
          "frameworkAssemblies": [],
          "runtimeAssemblies": [
            "lib/aspnetcore50/System.Net.Primitives.dll"
          ],
          "compileAssemblies": [
            "lib/contract/System.Net.Primitives.dll"
          ]
        }
      },
      "files": [
        "License.rtf",
        "System.Net.Primitives.4.0.10-beta-22231.nupkg",
        "System.Net.Primitives.4.0.10-beta-22231.nupkg.sha512",
        "System.Net.Primitives.nuspec",
        "lib/aspnetcore50/System.Net.Primitives.dll",
        "lib/contract/System.Net.Primitives.dll"
      ]
    },
    "System.ObjectModel/4.0.10-beta-22816": {
      "serviceable": false,
      "sha": "Rtu5FLq7JTtignXiSEKx26Q01NHyoO3pTcYYdwF54kFC64VbHEcvs8b586JyVVpM7Wz0zBmdgHDrH9fv2MgeVw==",
      "frameworks": {
        "DNX,Version=v4.5.1": {
          "dependencies": {
            "System.Runtime": "4.0.20-beta-22816"
          },
          "frameworkAssemblies": [
            "mscorlib",
            "System"
          ],
          "runtimeAssemblies": [
            "lib/net45/System.ObjectModel.dll"
          ],
          "compileAssemblies": [
            "lib/net45/System.ObjectModel.dll"
          ]
        },
        "DNXCore,Version=v5.0": {
          "dependencies": {
            "System.Runtime": "4.0.20-beta-22816"
          },
          "frameworkAssemblies": [],
          "runtimeAssemblies": [
            "lib/aspnetcore50/System.ObjectModel.dll"
          ],
          "compileAssemblies": [
            "lib/contract/System.ObjectModel.dll"
          ]
        }
      },
      "files": [
        "License.rtf",
        "System.ObjectModel.4.0.10-beta-22816.nupkg",
        "System.ObjectModel.4.0.10-beta-22816.nupkg.sha512",
        "System.ObjectModel.nuspec",
        "lib/aspnetcore50/System.ObjectModel.dll",
        "lib/contract/System.ObjectModel.dll",
        "lib/net45/System.ObjectModel.dll",
        "lib/portable-wpa81+wp80+win80+net45+aspnetcore50/System.ObjectModel.dll"
      ]
    },
    "System.Reflection/4.0.10-beta-22816": {
      "serviceable": false,
      "sha": "vdH/6euCyI/0el+6baAh/pttTZyWDh/PfL2TebSri3+FvNkjIEcE4httMn7J/5Lqz+NMDcLP7wOlY4Aa5EazNg==",
      "frameworks": {
        "DNX,Version=v4.5.1": {
          "dependencies": {
            "System.IO": "4.0.10-beta-22816",
            "System.Reflection.Primitives": "4.0.0-beta-22816",
            "System.Runtime": "4.0.20-beta-22816"
          },
          "frameworkAssemblies": [
            "mscorlib"
          ],
          "runtimeAssemblies": [
            "lib/net45/System.Reflection.dll"
          ],
          "compileAssemblies": [
            "lib/net45/System.Reflection.dll"
          ]
        },
        "DNXCore,Version=v5.0": {
          "dependencies": {
            "System.IO": "4.0.10-beta-22816",
            "System.Reflection.Primitives": "4.0.0-beta-22816",
            "System.Runtime": "4.0.20-beta-22816"
          },
          "frameworkAssemblies": [],
          "runtimeAssemblies": [
            "lib/aspnetcore50/System.Reflection.dll"
          ],
          "compileAssemblies": [
            "lib/contract/System.Reflection.dll"
          ]
        }
      },
      "files": [
        "License.rtf",
        "System.Reflection.4.0.10-beta-22816.nupkg",
        "System.Reflection.4.0.10-beta-22816.nupkg.sha512",
        "System.Reflection.nuspec",
        "lib/aspnetcore50/System.Reflection.dll",
        "lib/contract/System.Reflection.dll",
        "lib/net45/System.Reflection.dll",
        "lib/portable-wpa81+wp80+win80+net45+aspnetcore50/System.Reflection.dll"
      ]
    },
    "System.Reflection.Primitives/4.0.0-beta-22816": {
      "serviceable": false,
      "sha": "LXGxjPbmTit9COY1WKRG89Eya58UFVqebeNvGDCrX/c/72OP9XX00+wUUE34WFDioKeVBjofOySFdtKMVsDq1Q==",
      "frameworks": {
        "DNX,Version=v4.5.1": {
          "dependencies": {
            "System.Runtime": "4.0.20-beta-22816"
          },
          "frameworkAssemblies": [
            "mscorlib"
          ],
          "runtimeAssemblies": [
            "lib/net45/System.Reflection.Primitives.dll"
          ],
          "compileAssemblies": [
            "lib/net45/System.Reflection.Primitives.dll"
          ]
        },
        "DNXCore,Version=v5.0": {
          "dependencies": {
            "System.Runtime": "4.0.20-beta-22816"
          },
          "frameworkAssemblies": [],
          "runtimeAssemblies": [
            "lib/aspnetcore50/System.Reflection.Primitives.dll"
          ],
          "compileAssemblies": [
            "lib/contract/System.Reflection.Primitives.dll"
          ]
        }
      },
      "files": [
        "License.rtf",
        "System.Reflection.Primitives.4.0.0-beta-22816.nupkg",
        "System.Reflection.Primitives.4.0.0-beta-22816.nupkg.sha512",
        "System.Reflection.Primitives.nuspec",
        "lib/aspnetcore50/System.Reflection.Primitives.dll",
        "lib/contract/System.Reflection.Primitives.dll",
        "lib/net45/System.Reflection.Primitives.dll",
        "lib/portable-wpa81+wp80+win80+net45+aspnetcore50/System.Reflection.Primitives.dll"
      ]
    },
    "System.Reflection.TypeExtensions/4.0.0-beta-22911": {
      "serviceable": false,
      "sha": "TtisaufeMW3YTXI3LiqgNMVlKV6JyrSNf14DrlsCSf1rZ1yY4uj5mN+D4wCq4/5o3yIONAM0elJF6HFUpWwPIQ==",
      "frameworks": {
        "DNX,Version=v4.5.1": {
          "dependencies": {
            "System.Reflection": "4.0.0-beta-22911",
            "System.Runtime": "4.0.0-beta-22911"
          },
          "frameworkAssemblies": [],
          "runtimeAssemblies": [],
          "compileAssemblies": []
        },
        "DNXCore,Version=v5.0": {
          "dependencies": {
            "System.Reflection": "4.0.0-beta-22911",
            "System.Runtime": "4.0.0-beta-22911"
          },
          "frameworkAssemblies": [],
          "runtimeAssemblies": [
            "lib/aspnetcore50/System.Reflection.TypeExtensions.dll"
          ],
          "compileAssemblies": [
            "lib/contract/System.Reflection.TypeExtensions.dll"
          ]
        }
      },
      "files": [
        "License.rtf",
        "System.Reflection.TypeExtensions.4.0.0-beta-22911.nupkg",
        "System.Reflection.TypeExtensions.4.0.0-beta-22911.nupkg.sha512",
        "System.Reflection.TypeExtensions.nuspec",
        "lib/aspnetcore50/System.Reflection.TypeExtensions.dll",
        "lib/contract/System.Reflection.TypeExtensions.dll",
        "lib/net45/_._",
        "lib/portable-wpa81+wp80+win80+net45+aspnetcore50/System.Reflection.TypeExtensions.dll"
      ]
    },
    "System.Runtime/4.0.20-beta-22816": {
      "serviceable": false,
      "sha": "sDSJEmM6Q5O7Nn9XxHTrsEJ4bv4hsBdeTWjuvyzd9/u9ujl9AWa3q1XFLrdPZetILPOC1P0+1LOCq4kZcsKF5Q==",
      "frameworks": {
        "DNX,Version=v4.5.1": {
          "dependencies": {},
          "frameworkAssemblies": [
            "mscorlib",
            "System",
            "System.ComponentModel.Composition",
            "System.Core"
          ],
          "runtimeAssemblies": [
            "lib/net45/System.Runtime.dll"
          ],
          "compileAssemblies": [
            "lib/net45/System.Runtime.dll"
          ]
        },
        "DNXCore,Version=v5.0": {
          "dependencies": {},
          "frameworkAssemblies": [],
          "runtimeAssemblies": [
            "lib/aspnetcore50/System.Runtime.dll"
          ],
          "compileAssemblies": [
            "lib/contract/System.Runtime.dll"
          ]
        }
      },
      "files": [
        "License.rtf",
        "System.Runtime.4.0.20-beta-22816.nupkg",
        "System.Runtime.4.0.20-beta-22816.nupkg.sha512",
        "System.Runtime.nuspec",
        "lib/aspnetcore50/System.Runtime.dll",
        "lib/contract/System.Runtime.dll",
        "lib/net45/System.Runtime.dll",
        "lib/portable-wpa81+wp80+win80+net45+aspnetcore50/System.Runtime.dll"
      ]
    },
    "System.Runtime.Extensions/4.0.10-beta-22231": {
      "serviceable": false,
      "sha": "NR2vPmWFLARY9YJ2zEVIGAx+2/xtUf/cRB8joLNFLnyePPreI1CuMEYi8rxwv4qQtNv3qeNAyp65uQC35WnIYA==",
      "frameworks": {
        "DNX,Version=v4.5.1": {
          "dependencies": {
            "System.Runtime": "4.0.0-beta-22231"
          },
          "frameworkAssemblies": [],
          "runtimeAssemblies": [],
          "compileAssemblies": []
        },
        "DNXCore,Version=v5.0": {
          "dependencies": {
            "System.Runtime": "4.0.0-beta-22231"
          },
          "frameworkAssemblies": [],
          "runtimeAssemblies": [
            "lib/aspnetcore50/System.Runtime.Extensions.dll"
          ],
          "compileAssemblies": [
            "lib/contract/System.Runtime.Extensions.dll"
          ]
        }
      },
      "files": [
        "License.rtf",
        "System.Runtime.Extensions.4.0.10-beta-22231.nupkg",
        "System.Runtime.Extensions.4.0.10-beta-22231.nupkg.sha512",
        "System.Runtime.Extensions.nuspec",
        "lib/aspnetcore50/System.Runtime.Extensions.dll",
        "lib/contract/System.Runtime.Extensions.dll"
      ]
    },
    "System.Runtime.Handles/4.0.0-beta-22231": {
      "serviceable": false,
      "sha": "cILC3Qv6uRiXorkEHEwQYyDuNAinG1U7YqP2b+/HEsPnPWVqePpm+L+2iNdHDehCM+mCUo9Wav6PPiwL4wfaxQ==",
      "frameworks": {
        "DNX,Version=v4.5.1": {
          "dependencies": {
            "System.Runtime": "4.0.0-beta-22231"
          },
          "frameworkAssemblies": [],
          "runtimeAssemblies": [],
          "compileAssemblies": []
        },
        "DNXCore,Version=v5.0": {
          "dependencies": {
            "System.Runtime": "4.0.0-beta-22231"
          },
          "frameworkAssemblies": [],
          "runtimeAssemblies": [
            "lib/aspnetcore50/System.Runtime.Handles.dll"
          ],
          "compileAssemblies": [
            "lib/contract/System.Runtime.Handles.dll"
          ]
        }
      },
      "files": [
        "License.rtf",
        "System.Runtime.Handles.4.0.0-beta-22231.nupkg",
        "System.Runtime.Handles.4.0.0-beta-22231.nupkg.sha512",
        "System.Runtime.Handles.nuspec",
        "lib/aspnetcore50/System.Runtime.Handles.dll",
        "lib/contract/System.Runtime.Handles.dll"
      ]
    },
    "System.Text.Encoding/4.0.10-beta-22816": {
      "serviceable": false,
      "sha": "QDKTAvat7aDGMWnVkGm6tJvvmc2zSTa/p8M4/OEBBkZKNx4SGkeGEjFUhl7b6AXZ220m4dACygkiAVoB/LqMHw==",
      "frameworks": {
        "DNX,Version=v4.5.1": {
          "dependencies": {
            "System.Runtime": "4.0.20-beta-22816"
          },
          "frameworkAssemblies": [
            "mscorlib"
          ],
          "runtimeAssemblies": [
            "lib/net45/System.Text.Encoding.dll"
          ],
          "compileAssemblies": [
            "lib/net45/System.Text.Encoding.dll"
          ]
        },
        "DNXCore,Version=v5.0": {
          "dependencies": {
            "System.Runtime": "4.0.20-beta-22816"
          },
          "frameworkAssemblies": [],
          "runtimeAssemblies": [
            "lib/aspnetcore50/System.Text.Encoding.dll"
          ],
          "compileAssemblies": [
            "lib/contract/System.Text.Encoding.dll"
          ]
        }
      },
      "files": [
        "License.rtf",
        "System.Text.Encoding.4.0.10-beta-22816.nupkg",
        "System.Text.Encoding.4.0.10-beta-22816.nupkg.sha512",
        "System.Text.Encoding.nuspec",
        "lib/aspnetcore50/System.Text.Encoding.dll",
        "lib/contract/System.Text.Encoding.dll",
        "lib/net45/System.Text.Encoding.dll",
        "lib/portable-wpa81+wp80+win80+net45+aspnetcore50/System.Text.Encoding.dll"
      ]
    },
    "System.Text.RegularExpressions/4.0.10-beta-22911": {
      "serviceable": false,
      "sha": "64gqmVWF9xWL2ksAVZW3EwazntHzvCTi1R8nVuZKIanxUUKrAkkHY+LdxH/HFtIqxa5xe5VjKZJo8k4KPRj4Qw==",
      "frameworks": {
        "DNX,Version=v4.5.1": {
          "dependencies": {
            "System.Runtime": "4.0.0-beta-22911"
          },
          "frameworkAssemblies": [],
          "runtimeAssemblies": [
            "lib/net45/System.Text.RegularExpressions.dll"
          ],
          "compileAssemblies": [
            "lib/net45/System.Text.RegularExpressions.dll"
          ]
        },
        "DNXCore,Version=v5.0": {
          "dependencies": {
            "System.Runtime": "4.0.0-beta-22911"
          },
          "frameworkAssemblies": [],
          "runtimeAssemblies": [
            "lib/aspnetcore50/System.Text.RegularExpressions.dll"
          ],
          "compileAssemblies": [
            "lib/contract/System.Text.RegularExpressions.dll"
          ]
        }
      },
      "files": [
        "License.rtf",
        "System.Text.RegularExpressions.4.0.10-beta-22911.nupkg",
        "System.Text.RegularExpressions.4.0.10-beta-22911.nupkg.sha512",
        "System.Text.RegularExpressions.nuspec",
        "lib/aspnetcore50/System.Text.RegularExpressions.dll",
        "lib/contract/System.Text.RegularExpressions.dll",
        "lib/net45/System.Text.RegularExpressions.dll",
        "lib/portable-wpa81+wp80+win80+net45+aspnetcore50/System.Text.RegularExpressions.dll"
      ]
    },
    "System.Threading/4.0.10-beta-22816": {
      "serviceable": false,
      "sha": "tNAZqIJaAhnHpiEJdvGby7EFfirhD3aX+FF6vQBnHrk+bWVv4yAQ3k/skF7FBJIhMozenT41/1QVVwtTSR3HOQ==",
      "frameworks": {
        "DNX,Version=v4.5.1": {
          "dependencies": {
            "System.Runtime": "4.0.20-beta-22816",
            "System.Threading.Tasks": "4.0.10-beta-22816"
          },
          "frameworkAssemblies": [
            "mscorlib",
            "System",
            "System.Core"
          ],
          "runtimeAssemblies": [
            "lib/net45/System.Threading.dll"
          ],
          "compileAssemblies": [
            "lib/net45/System.Threading.dll"
          ]
        },
        "DNXCore,Version=v5.0": {
          "dependencies": {
            "System.Runtime": "4.0.20-beta-22816",
            "System.Threading.Tasks": "4.0.10-beta-22816"
          },
          "frameworkAssemblies": [],
          "runtimeAssemblies": [
            "lib/aspnetcore50/System.Threading.dll"
          ],
          "compileAssemblies": [
            "lib/contract/System.Threading.dll"
          ]
        }
      },
      "files": [
        "License.rtf",
        "System.Threading.4.0.10-beta-22816.nupkg",
        "System.Threading.4.0.10-beta-22816.nupkg.sha512",
        "System.Threading.nuspec",
        "lib/aspnetcore50/System.Threading.dll",
        "lib/contract/System.Threading.dll",
        "lib/net45/System.Threading.dll",
        "lib/portable-wpa81+wp80+win80+net45+aspnetcore50/System.Threading.dll"
      ]
    },
    "System.Threading.Tasks/4.0.10-beta-22816": {
      "serviceable": false,
      "sha": "e7TcoQuIPQ4bvkkCY2ulU8NFvj8XqYxsGpD3fAq1KajAlpx5j327Q13lKxlGPb7ouHQydKHCy5G1ZGuydb0DAA==",
      "frameworks": {
        "DNX,Version=v4.5.1": {
          "dependencies": {
            "System.Runtime": "4.0.20-beta-22816"
          },
          "frameworkAssemblies": [
            "mscorlib",
            "System.Core"
          ],
          "runtimeAssemblies": [
            "lib/net45/System.Threading.Tasks.dll"
          ],
          "compileAssemblies": [
            "lib/net45/System.Threading.Tasks.dll"
          ]
        },
        "DNXCore,Version=v5.0": {
          "dependencies": {
            "System.Runtime": "4.0.20-beta-22816"
          },
          "frameworkAssemblies": [],
          "runtimeAssemblies": [
            "lib/aspnetcore50/System.Threading.Tasks.dll"
          ],
          "compileAssemblies": [
            "lib/contract/System.Threading.Tasks.dll"
          ]
        }
      },
      "files": [
        "License.rtf",
        "System.Threading.Tasks.4.0.10-beta-22816.nupkg",
        "System.Threading.Tasks.4.0.10-beta-22816.nupkg.sha512",
        "System.Threading.Tasks.nuspec",
        "lib/aspnetcore50/System.Threading.Tasks.dll",
        "lib/contract/System.Threading.Tasks.dll",
        "lib/net45/System.Threading.Tasks.dll",
        "lib/portable-wpa81+wp80+win80+net45+aspnetcore50/System.Threading.Tasks.dll"
      ]
    },
    "System.Xml.ReaderWriter/4.0.10-beta-22821": {
      "serviceable": false,
      "sha": "mqCU5/2fq5davYrGdnFjWb1ydy0S88D1x+WpnatPm1OkZvg5OOVWHiyMeQ1vSroQBmPN7pCGq//E9QPBT0MAcA==",
      "frameworks": {
        "DNX,Version=v4.5.1": {
          "dependencies": {
            "System.IO": "4.0.0-beta-22821",
            "System.Runtime": "4.0.0-beta-22821",
            "System.Text.Encoding": "4.0.0-beta-22821",
            "System.Threading.Tasks": "4.0.0-beta-22821"
          },
          "frameworkAssemblies": [],
          "runtimeAssemblies": [
            "lib/net45/System.Xml.ReaderWriter.dll"
          ],
          "compileAssemblies": [
            "lib/net45/System.Xml.ReaderWriter.dll"
          ]
        },
        "DNXCore,Version=v5.0": {
          "dependencies": {
            "System.IO": "4.0.0-beta-22821",
            "System.Runtime": "4.0.0-beta-22821",
            "System.Text.Encoding": "4.0.0-beta-22821",
            "System.Threading.Tasks": "4.0.0-beta-22821"
          },
          "frameworkAssemblies": [],
          "runtimeAssemblies": [
            "lib/aspnetcore50/System.Xml.ReaderWriter.dll"
          ],
          "compileAssemblies": [
            "lib/contract/System.Xml.ReaderWriter.dll"
          ]
        }
      },
      "files": [
        "License.rtf",
        "System.Xml.ReaderWriter.4.0.10-beta-22821.nupkg",
        "System.Xml.ReaderWriter.4.0.10-beta-22821.nupkg.sha512",
        "System.Xml.ReaderWriter.nuspec",
        "lib/aspnetcore50/System.Xml.ReaderWriter.dll",
        "lib/contract/System.Xml.ReaderWriter.dll",
        "lib/net45/System.Xml.ReaderWriter.dll",
        "lib/portable-wpa81+wp80+win80+net45+aspnetcore50/System.Xml.ReaderWriter.dll"
      ]
    },
    "System.Xml.XDocument/4.0.10-beta-22816": {
      "serviceable": false,
      "sha": "FcCtcZGfIC53KE0X9afERg0lLEJnXBQBAZG0wc0cSsklju2aZrXRS6QWOMMr91LLPJAefeTEoyrDw2LoXbp/Ww==",
      "frameworks": {
        "DNX,Version=v4.5.1": {
          "dependencies": {
            "System.IO": "4.0.10-beta-22816",
            "System.Runtime": "4.0.20-beta-22816",
            "System.Xml.ReaderWriter": "4.0.10-beta-22816"
          },
          "frameworkAssemblies": [
            "mscorlib",
            "System.Xml.Linq"
          ],
          "runtimeAssemblies": [
            "lib/net45/System.Xml.XDocument.dll"
          ],
          "compileAssemblies": [
            "lib/net45/System.Xml.XDocument.dll"
          ]
        },
        "DNXCore,Version=v5.0": {
          "dependencies": {
            "System.IO": "4.0.10-beta-22816",
            "System.Runtime": "4.0.20-beta-22816",
            "System.Xml.ReaderWriter": "4.0.10-beta-22816"
          },
          "frameworkAssemblies": [],
          "runtimeAssemblies": [
            "lib/aspnetcore50/System.Xml.XDocument.dll"
          ],
          "compileAssemblies": [
            "lib/contract/System.Xml.XDocument.dll"
          ]
        }
      },
      "files": [
        "License.rtf",
        "System.Xml.XDocument.4.0.10-beta-22816.nupkg",
        "System.Xml.XDocument.4.0.10-beta-22816.nupkg.sha512",
        "System.Xml.XDocument.nuspec",
        "lib/aspnetcore50/System.Xml.XDocument.dll",
        "lib/contract/System.Xml.XDocument.dll",
        "lib/net45/System.Xml.XDocument.dll",
        "lib/portable-wpa81+wp80+win80+net45+aspnetcore50/System.Xml.XDocument.dll"
      ]
    }
  }
}